dora_gradio/__init__.py
dora_gradio/__main__.py
dora_gradio/main.py
dora_gradio-0.4.1.dist-info/METADATA
dora_gradio-0.4.1.dist-info/WHEEL
dora_gradio-0.4.1.dist-info/entry_points.txt
dora_gradio-0.4.1.dist-info/top_level.txt
dora_gradio-0.4.1.dist-info/RECORD
