Metadata-Version: 2.4
Name: dora-gradio
Version: 0.4.1
Summary: dora-gradio
Author-email: Shashwat Patil <email@email.com>
License: MIT
Requires-Python: >=3.10
Requires-Dist: dora-rs>=0.3.9
Requires-Dist: gradio>=5.3.0
Requires-Dist: pyarrow>=14.0.1
Requires-Dist: numpy>=1.26.0
Requires-Dist: opencv-python>=4.8.0
Requires-Dist: fastrtc>=0.0.16
Requires-Dist: librosa>=0.10.1
